setup.py
appengine_auth/__init__.py
appengine_auth/backends.py
appengine_auth/models.py
appengine_auth/pipelines.py
django_appengine_auth.egg-info/PKG-INFO
django_appengine_auth.egg-info/SOURCES.txt
django_appengine_auth.egg-info/dependency_links.txt
django_appengine_auth.egg-info/requires.txt
django_appengine_auth.egg-info/top_level.txt