Metadata-Version: 1.1
Name: django-appengine-auth
Version: 1.0
Summary: django-appengine-auth is an extension to django-social-auth with a backend for the Google App Engine OAuth endpoint
Home-page: https://github.com/mback2k/django-appengine-auth
Author: Marc Hoersken
Author-email: info@marc-hoersken.de
License: MIT
Platform: UNKNOWN
Classifier: Topic :: Internet :: WWW/HTTP :: Dynamic Content
Classifier: Intended Audience :: Developers
Classifier: License :: OSI Approved :: MIT License
Classifier: Programming Language :: Python
Classifier: Topic :: Software Development :: Libraries :: Python Modules
Classifier: Development Status :: 4 - Beta
Classifier: Operating System :: OS Independent
